MANIFEST.in
README
README.md
setup.py
bin/install-repo
wheeljack/__init__.py
wheeljack/config.py
wheeljack/exceptions.py
wheeljack/install.py
wheeljack_repoman.egg-info/PKG-INFO
wheeljack_repoman.egg-info/SOURCES.txt
wheeljack_repoman.egg-info/dependency_links.txt
wheeljack_repoman.egg-info/requires.txt
wheeljack_repoman.egg-info/top_level.txt