Metadata-Version: 1.0
Name: wheeljack-repoman
Version: 0.3
Summary: UNKNOWN
Home-page: https://github.com/davedash/wheeljack
Author: Dave Dash
Author-email: dd+github@davedash.com
License: UNKNOWN
Platform: UNKNOWN
